__init__.py
coretool/__init__.py
coretool/api.py
coretool/apitools/ApiRestAbstractController.py
coretool/apitools/ApiRestStandard.py
coretool/apitools/__init__.py
coretool/apitools/apibasiccontroller.py
coretool/apitools/apirestbase.py
coretool/apitools/crudbasic.py
coretool/multi/asyncio.py
coretool/multi/futures.py
coretool/multi/processing.py
coretool/multi/threading.py
coretool/tools/__init__.py
coretool/tools/barcodegen.py
coretool/tools/base.py
coretool/tools/classes.py
coretool/tools/csv.py
coretool/tools/datetime.py
coretool/tools/dbsync.py
coretool/tools/decorators.py
coretool/tools/files.py
coretool/tools/filters.py
coretool/tools/images.py
coretool/tools/json.py
coretool/tools/net.py
coretool/tools/objects.py
coretool/tools/response.py
coretool/tools/strings.py
coretool/tools/validators.py
coretool/tools/djangoadmin/html.py
coretool/tools/djangoadmin/http.py
coretool/tools/djangoadmin/models.py
coretool/tools/djangoadmin/smart_selects/__init__.py
coretool/tools/djangoadmin/smart_selects/db_fields.py
coretool/tools/djangoadmin/smart_selects/form_fields.py
coretool/tools/djangoadmin/smart_selects/models.py
coretool/tools/djangoadmin/smart_selects/tests.py
coretool/tools/djangoadmin/smart_selects/urls.py
coretool/tools/djangoadmin/smart_selects/utils.py
coretool/tools/djangoadmin/smart_selects/views.py
coretool/tools/djangoadmin/smart_selects/widgets.py
coretool/tools/reportlab/base.py
coretool/tools/reportlab/simple.py
coretool/tools/reports/admin.py
coretool/tools/reports/lib.py
coretool/tools/tests/images/image_compressor_example.py
coretool/users/users.py
coretool_app/__init__.py
coretool_app/admin.py
coretool_app/base.py
coretool_app/fields.py
coretool_app/pstruct.py
coretool_app/admins/cronjobs.py
coretool_app/admins/errors.py
coretool_app/checks/__init__.py
coretool_app/checks/complexmodelcheck.py
coretool_app/checks/messages.py
coretool_app/controllers/__init__.py
coretool_app/controllers/cronjobs.py
coretool_app/controllers/errors.py
coretool-0.0.8.dist-info/LICENSE
coretool-0.0.8.dist-info/METADATA
coretool-0.0.8.dist-info/WHEEL
coretool-0.0.8.dist-info/top_level.txt
coretool-0.0.8.dist-info/RECORD
