Metadata-Version: 2.1
Name: coretool
Version: 0.0.8
Summary: Multi tools for every
Author-email: thotenn <joseenriquegaray@hotmail.com>
License: Copyright (c) 2023 THB
Project-URL: Homepage, https://github.com/thotenn/coretools
Project-URL: Bug Tracker, https://github.com/thotenn/coretools/issues
Keywords: coretools,core,tools
Classifier: Programming Language :: Python :: 3
Classifier: License :: OSI Approved :: MIT License
Requires-Python: >=3.7
License-File: LICENSE
Provides-Extra: build
Requires-Dist: build ; extra == 'build'
Requires-Dist: twine ; extra == 'build'
